pyreliabilitypro/__init__.py
pyreliabilitypro/core/__init__.py
pyreliabilitypro/core/distributions.py
pyreliabilitypro/core/metrics.py
pyreliabilitypro-0.2.0.dist-info/METADATA
pyreliabilitypro-0.2.0.dist-info/WHEEL
pyreliabilitypro-0.2.0.dist-info/top_level.txt
pyreliabilitypro-0.2.0.dist-info/RECORD
