Metadata-Version: 2.4
Name: pyreliabilitypro
Version: 0.2.0
Summary: A Python toolkit for reliability analysis (MTTF, Weibull) with CI/CD.
Author-email: Santtosh Muniyandy <santtosh6783@gmail.com>
Project-URL: Homepage, https://github.com/Santtosh19/PyReliabilityPro
Project-URL: Bug Tracker, https://github.com/Santtosh19/PyReliabilityPro/issues
Project-URL: Repository, https://github.com/Santtosh19/PyReliabilityPro
Keywords: reliability,weibull,mttf,failure analysis,statistics,engineering
Classifier: Development Status :: 3 - Alpha
Classifier: Intended Audience :: Developers
Classifier: Intended Audience :: Science/Research
Classifier: Intended Audience :: Education
Classifier: License :: OSI Approved :: MIT License
Classifier: Operating System :: OS Independent
Classifier: Programming Language :: Python :: 3
Classifier: Programming Language :: Python :: 3.8
Classifier: Programming Language :: Python :: 3.9
Classifier: Programming Language :: Python :: 3.10
Classifier: Programming Language :: Python :: 3.11
Classifier: Topic :: Scientific/Engineering
Classifier: Topic :: Software Development :: Libraries :: Python Modules
Requires-Python: >=3.8
Requires-Dist: numpy
Requires-Dist: scipy
